estudos/interfaces-seriais/uart_tx.v
module uart_tx ( // 8-E-2
    input clk,
    input rst,
    input tx_start,
    input [7:0] data, // [MSB:LSB]
    output reg tx // bit serrial saindo
);  
    // converter o clock para a frequencia de transmissão
    parameter CLK_FREQ = 50_000_000; // Ex. FPGA com 50MHZ
    parameter BAUD_RATE = 9600; // faixa de transmissão
    localparam DIVISOR = CLK_FREQ / BAUD_RATE;

    // quantos bits um reg precisa ter para represetar um númerO? Nesse caso o do DIVISOR
    // $clog2(N) retorna o menor número de bits que consegue representar N valores diferentes (de 0 a N-1)
    /* 
        DIVISOR = 5208
        2^12 = 4096 → só representa valores de 0 a 4095. Não é suficiente (5207 > 4095).
        2^13 = 8192 → representa valores de 0 a 8191. Suficiente.
        Como 12 bits não bastam e 13 bastam, $clog2(5208) = 13.
    */
    parameter largura = $clog2(DIVISOR)-1;
    reg [largura : 0] contador;
    reg baud_tick; // 

    always @(posedge clk) begin
        if (rst) begin
            contador <= 0;
            baud_tick <= 0;
        end
        else if (contador == DIVISOR - 1) begin
            baud_tick <= 1;
            contador <= 0;
        end
        else begin
            baud_tick <= 0;
            contador <= contador + 1;
        end
    end

    // Máquina de estados

    reg [2 : 0] state;  // até 8 estados
    reg [2 : 0] bit_index; // mostra o indice o bit que está sendo transmitido, 3 bits pois 2^3 = 8 representações
    reg [7 : 0] data_reg;  // guarda os dados para não perder no meio da transmissão 
    reg parity_bit;

    localparam IDLE   = 3'd0, // <largura em bits>'<base><valor>
               START  = 3'd1,
               DATA   = 3'd2,
               PARITY = 3'd3,
               STOP1  = 3'd4,
               STOP2  = 3'd5;
    
    always @(posedge clk) begin
        if (rst) begin
            state <= IDLE;
            bit_index <= 0;
            tx <= 1;
        end
        else if (baud_tick) begin
            case (state)
                IDLE: begin
                    if (tx_start) begin
                        tx <= 1;
                        data_reg <= data;
                        parity_bit <= ^data;
                        state <= START;
                    end
                end 
                START: begin
                    tx <= 0;
                    bit_index <= 0;
                    state <= DATA;
                end
                DATA: begin
                    tx <= data_reg[bit_index];
                    if (bit_index != 7) begin
                        bit_index <= bit_index + 1;
                        state <= DATA;
                    end
                    else begin
                        state <= PARITY;
                    end
                end
                PARITY: begin
                    tx <= parity_bit;
                    state <= STOP1;
                end
                STOP1: begin
                    tx <= 1;
                    state <= STOP2;
                end
                STOP2: begin
                    tx <= 1;
                    state <= IDLE;
                end
                default: state <= IDLE;
            endcase
        end
    end
endmodule

estudos/interfaces-seriais/uart_tx_tb.v
`timescale 1ns/1ps

module uart_tx_tb;

    reg clk;
    reg rst;
    reg tx_start;
    reg [7:0] data;
    wire tx;

    // DIVISOR pequeno (100 / 10 = 10 ciclos por bit) só para a simulação
    // ficar rápida e fácil de ler no GTKWave. Os valores default
    // (50_000_000 / 9600) continuam sendo os usados em hardware real.
    uart_tx #(
        .CLK_FREQ(100),
        .BAUD_RATE(10)
    ) dut (
        .clk(clk),
        .rst(rst),
        .tx_start(tx_start),
        .data(data),
        .tx(tx)
    );

    // Clock de 10ns de período (100MHz "simulado")
    initial clk = 0;
    always #5 clk = ~clk;

    initial begin
        $dumpfile("dump.vcd");
        $dumpvars(0, uart_tx_tb);

        rst      = 1;
        tx_start = 0;
        data     = 8'h55; // 01010101 - alterna 0/1, fácil de ver na forma de onda

        #50;       // segura o reset por 5 ciclos de clock
        rst = 0;
        #20;       // settle antes de iniciar a transmissão

        tx_start = 1;
        #100;      // segura tx_start por 1 período de baud inteiro (10 ciclos)
                    // garante que o baud_tick "veja" o tx_start em IDLE
        tx_start = 0;

        // 1 frame = 12 bits (8-E-2) * 10 ciclos/bit * 10ns/ciclo = 1200ns
        // espera o frame inteiro terminar, com folga
        #1500;

        $finish;
    end

endmodule

estudos/interfaces-seriais/dump.vcd
$date
	Wed Jun 17 00:07:06 2026
$end
$version
	Icarus Verilog
$end
$timescale
	1ps
$end
$scope module uart_tx_tb $end
$var wire 1 ! tx $end
$var reg 1 " clk $end
$var reg 8 # data [7:0] $end
$var reg 1 $ rst $end
$var reg 1 % tx_start $end
$scope module dut $end
$var wire 1 " clk $end
$var wire 8 & data [7:0] $end
$var wire 1 $ rst $end
$var wire 1 % tx_start $end
$var parameter 32 ' BAUD_RATE $end
$var parameter 32 ( CLK_FREQ $end
$var parameter 3 ) DATA $end
$var parameter 32 * DIVISOR $end
$var parameter 3 + IDLE $end
$var parameter 3 , PARITY $end
$var parameter 3 - START $end
$var parameter 3 . STOP1 $end
$var parameter 3 / STOP2 $end
$var parameter 33 0 largura $end
$var reg 1 1 baud_tick $end
$var reg 3 2 bit_index [2:0] $end
$var reg 4 3 contador [3:0] $end
$var reg 8 4 data_reg [7:0] $end
$var reg 1 5 parity_bit $end
$var reg 3 6 state [2:0] $end
$var reg 1 ! tx $end
$upscope $end
$upscope $end
$enddefinitions $end
$comment Show the parameter values. $end
$dumpall
b11 0
b101 /
b100 .
b1 -
b11 ,
b0 +
b1010 *
b10 )
b1100100 (
b1010 '
$end
#0
$dumpvars
bx 6
x5
bx 4
bx 3
bx 2
x1
b1010101 &
0%
1$
b1010101 #
0"
x!
$end
#5000
01
b0 3
1!
b0 2
b0 6
1"
#10000
0"
#15000
1"
#20000
0"
#25000
1"
#30000
0"
#35000
1"
#40000
0"
#45000
1"
#50000
0"
0$
#55000
b1 3
1"
#60000
0"
#65000
b10 3
1"
#70000
0"
1%
#75000
b11 3
1"
#80000
0"
#85000
b100 3
1"
#90000
0"
#95000
b101 3
1"
#100000
0"
#105000
b110 3
1"
#110000
0"
#115000
b111 3
1"
#120000
0"
#125000
b1000 3
1"
#130000
0"
#135000
b1001 3
1"
#140000
0"
#145000
b0 3
11
1"
#150000
0"
#155000
b1 6
05
b1010101 4
b1 3
01
1"
#160000
0"
#165000
b10 3
1"
#170000
0"
0%
#175000
b11 3
1"
#180000
0"
#185000
b100 3
1"
#190000
0"
#195000
b101 3
1"
#200000
0"
#205000
b110 3
1"
#210000
0"
#215000
b111 3
1"
#220000
0"
#225000
b1000 3
1"
#230000
0"
#235000
b1001 3
1"
#240000
0"
#245000
b0 3
11
1"
#250000
0"
#255000
b10 6
0!
b1 3
01
1"
#260000
0"
#265000
b10 3
1"
#270000
0"
#275000
b11 3
1"
#280000
0"
#285000
b100 3
1"
#290000
0"
#295000
b101 3
1"
#300000
0"
#305000
b110 3
1"
#310000
0"
#315000
b111 3
1"
#320000
0"
#325000
b1000 3
1"
#330000
0"
#335000
b1001 3
1"
#340000
0"
#345000
b0 3
11
1"
#350000
0"
#355000
b1 2
1!
b1 3
01
1"
#360000
0"
#365000
b10 3
1"
#370000
0"
#375000
b11 3
1"
#380000
0"
#385000
b100 3
1"
#390000
0"
#395000
b101 3
1"
#400000
0"
#405000
b110 3
1"
#410000
0"
#415000
b111 3
1"
#420000
0"
#425000
b1000 3
1"
#430000
0"
#435000
b1001 3
1"
#440000
0"
#445000
b0 3
11
1"
#450000
0"
#455000
b10 2
0!
b1 3
01
1"
#460000
0"
#465000
b10 3
1"
#470000
0"
#475000
b11 3
1"
#480000
0"
#485000
b100 3
1"
#490000
0"
#495000
b101 3
1"
#500000
0"
#505000
b110 3
1"
#510000
0"
#515000
b111 3
1"
#520000
0"
#525000
b1000 3
1"
#530000
0"
#535000
b1001 3
1"
#540000
0"
#545000
b0 3
11
1"
#550000
0"
#555000
b11 2
1!
b1 3
01
1"
#560000
0"
#565000
b10 3
1"
#570000
0"
#575000
b11 3
1"
#580000
0"
#585000
b100 3
1"
#590000
0"
#595000
b101 3
1"
#600000
0"
#605000
b110 3
1"
#610000
0"
#615000
b111 3
1"
#620000
0"
#625000
b1000 3
1"
#630000
0"
#635000
b1001 3
1"
#640000
0"
#645000
b0 3
11
1"
#650000
0"
#655000
b100 2
0!
b1 3
01
1"
#660000
0"
#665000
b10 3
1"
#670000
0"
#675000
b11 3
1"
#680000
0"
#685000
b100 3
1"
#690000
0"
#695000
b101 3
1"
#700000
0"
#705000
b110 3
1"
#710000
0"
#715000
b111 3
1"
#720000
0"
#725000
b1000 3
1"
#730000
0"
#735000
b1001 3
1"
#740000
0"
#745000
b0 3
11
1"
#750000
0"
#755000
b101 2
1!
b1 3
01
1"
#760000
0"
#765000
b10 3
1"
#770000
0"
#775000
b11 3
1"
#780000
0"
#785000
b100 3
1"
#790000
0"
#795000
b101 3
1"
#800000
0"
#805000
b110 3
1"
#810000
0"
#815000
b111 3
1"
#820000
0"
#825000
b1000 3
1"
#830000
0"
#835000
b1001 3
1"
#840000
0"
#845000
b0 3
11
1"
#850000
0"
#855000
b110 2
0!
b1 3
01
1"
#860000
0"
#865000
b10 3
1"
#870000
0"
#875000
b11 3
1"
#880000
0"
#885000
b100 3
1"
#890000
0"
#895000
b101 3
1"
#900000
0"
#905000
b110 3
1"
#910000
0"
#915000
b111 3
1"
#920000
0"
#925000
b1000 3
1"
#930000
0"
#935000
b1001 3
1"
#940000
0"
#945000
b0 3
11
1"
#950000
0"
#955000
b111 2
1!
b1 3
01
1"
#960000
0"
#965000
b10 3
1"
#970000
0"
#975000
b11 3
1"
#980000
0"
#985000
b100 3
1"
#990000
0"
#995000
b101 3
1"
#1000000
0"
#1005000
b110 3
1"
#1010000
0"
#1015000
b111 3
1"
#1020000
0"
#1025000
b1000 3
1"
#1030000
0"
#1035000
b1001 3
1"
#1040000
0"
#1045000
b0 3
11
1"
#1050000
0"
#1055000
b11 6
0!
b1 3
01
1"
#1060000
0"
#1065000
b10 3
1"
#1070000
0"
#1075000
b11 3
1"
#1080000
0"
#1085000
b100 3
1"
#1090000
0"
#1095000
b101 3
1"
#1100000
0"
#1105000
b110 3
1"
#1110000
0"
#1115000
b111 3
1"
#1120000
0"
#1125000
b1000 3
1"
#1130000
0"
#1135000
b1001 3
1"
#1140000
0"
#1145000
b0 3
11
1"
#1150000
0"
#1155000
b100 6
b1 3
01
1"
#1160000
0"
#1165000
b10 3
1"
#1170000
0"
#1175000
b11 3
1"
#1180000
0"
#1185000
b100 3
1"
#1190000
0"
#1195000
b101 3
1"
#1200000
0"
#1205000
b110 3
1"
#1210000
0"
#1215000
b111 3
1"
#1220000
0"
#1225000
b1000 3
1"
#1230000
0"
#1235000
b1001 3
1"
#1240000
0"
#1245000
b0 3
11
1"
#1250000
0"
#1255000
b101 6
1!
b1 3
01
1"
#1260000
0"
#1265000
b10 3
1"
#1270000
0"
#1275000
b11 3
1"
#1280000
0"
#1285000
b100 3
1"
#1290000
0"
#1295000
b101 3
1"
#1300000
0"
#1305000
b110 3
1"
#1310000
0"
#1315000
b111 3
1"
#1320000
0"
#1325000
b1000 3
1"
#1330000
0"
#1335000
b1001 3
1"
#1340000
0"
#1345000
b0 3
11
1"
#1350000
0"
#1355000
b0 6
b1 3
01
1"
#1360000
0"
#1365000
b10 3
1"
#1370000
0"
#1375000
b11 3
1"
#1380000
0"
#1385000
b100 3
1"
#1390000
0"
#1395000
b101 3
1"
#1400000
0"
#1405000
b110 3
1"
#1410000
0"
#1415000
b111 3
1"
#1420000
0"
#1425000
b1000 3
1"
#1430000
0"
#1435000
b1001 3
1"
#1440000
0"
#1445000
b0 3
11
1"
#1450000
0"
#1455000
b1 3
01
1"
#1460000
0"
#1465000
b10 3
1"
#1470000
0"
#1475000
b11 3
1"
#1480000
0"
#1485000
b100 3
1"
#1490000
0"
#1495000
b101 3
1"
#1500000
0"
#1505000
b110 3
1"
#1510000
0"
#1515000
b111 3
1"
#1520000
0"
#1525000
b1000 3
1"
#1530000
0"
#1535000
b1001 3
1"
#1540000
0"
#1545000
b0 3
11
1"
#1550000
0"
#1555000
b1 3
01
1"
#1560000
0"
#1565000
b10 3
1"
#1570000
0"
#1575000
b11 3
1"
#1580000
0"
#1585000
b100 3
1"
#1590000
0"
#1595000
b101 3
1"
#1600000
0"
#1605000
b110 3
1"
#1610000
0"
#1615000
b111 3
1"
#1620000
0"
#1625000
b1000 3
1"
#1630000
0"
#1635000
b1001 3
1"
#1640000
0"
#1645000
b0 3
11
1"
#1650000
0"
#1655000
b1 3
01
1"
#1660000
0"
#1665000
b10 3
1"
